README.md
setup.py
Deep_Models.egg-info/PKG-INFO
Deep_Models.egg-info/SOURCES.txt
Deep_Models.egg-info/dependency_links.txt
Deep_Models.egg-info/requires.txt
Deep_Models.egg-info/top_level.txt
deep_models/__init__.py
deep_models/wide_residual_network.py