Metadata-Version: 1.0
Name: Deep-Models
Version: 0.1.5
Summary: Keras deep learning model implementations
Home-page: https://github.com/tayden/DeepModels
Author: Taylor Denouden
Author-email: taylordenouden@gmail.com
License: MIT
Platform: UNKNOWN
